odoo/addons/mrp_repair_reuse_component/README.rst
odoo/addons/mrp_repair_reuse_component/__init__.py
odoo/addons/mrp_repair_reuse_component/__manifest__.py
odoo/addons/mrp_repair_reuse_component/i18n/it.po
odoo/addons/mrp_repair_reuse_component/i18n/mrp_repair_reuse_component.pot
odoo/addons/mrp_repair_reuse_component/models/__init__.py
odoo/addons/mrp_repair_reuse_component/models/product.py
odoo/addons/mrp_repair_reuse_component/readme/CONTRIBUTORS.md
odoo/addons/mrp_repair_reuse_component/readme/DESCRIPTION.md
odoo/addons/mrp_repair_reuse_component/static/description/icon.png
odoo/addons/mrp_repair_reuse_component/static/description/index.html
odoo/addons/mrp_repair_reuse_component/tests/__init__.py
odoo/addons/mrp_repair_reuse_component/tests/test_mrp_repair_reuse_component.py
odoo14_addon_mrp_repair_reuse_component-14.0.1.0.1.dev4.dist-info/METADATA
odoo14_addon_mrp_repair_reuse_component-14.0.1.0.1.dev4.dist-info/WHEEL
odoo14_addon_mrp_repair_reuse_component-14.0.1.0.1.dev4.dist-info/top_level.txt
odoo14_addon_mrp_repair_reuse_component-14.0.1.0.1.dev4.dist-info/RECORD
